[
  {
    "answer": "At Retirement /Exit , you can withdraw a maximum of <b>₹Rs. $i /- </b> (i.e 60% of the total maturity amount ).",
    "calId": "-MJCuzljMK8EUVziz6Ze",
    "firebaseId": "-MJS2ymJy__u9QUYGq6O",
    "ques": ""
  },
  {
    "answer": "You have to invest the remaining  <b> ₹ $j /- </b> to purchase the pension fund.",
    "calId": "-MJCuzljMK8EUVziz6Ze",
    "firebaseId": "-MJS3GvEOMDkymzQQ-ma",
    "ques": ""
  },
  {
    "answer": "After Retirement / Exit , you will get monthly Pension of <b> ₹ @ 0.01 * j * r * 0.083334  @ /-</b> throughout  your life .",
    "calId": "-MJCuzljMK8EUVziz6Ze",
    "firebaseId": "-MJS4sQ9-V0K0mEt6EJD",
    "ques": ""
  },
  {
    "answer": "At the end of your life , the pension deposit amount <b> $j /- </b> will be given back to your nominees.",
    "calId": "-MJCuzljMK8EUVziz6Ze",
    "firebaseId": "-MJS5Fpr-TH3bmR9AePr",
    "ques": ""
  }
]
